{
  "modelID": "lq_taxpayer", 
  "fields": [
    {"field":"id","name":"ID","dataType":"bigint"},
    {"field":"nsrsbh","name":"机构ID","dataType":"varchar","fieldType":"many2one","relatedModelID":"lq_legal_entity","quickSearch":true},
    {"field":"djxh","name":"登记序号","dataType":"varchar","quickSearch":true},
    {"field":"ssdabh","name":"税收档案编号","dataType":"varchar","quickSearch":true},
    {"field":"nsrmc","name":"纳税人名称","dataType":"varchar","quickSearch":true},
    {"field":"nsrlx","name":"纳税人类型标签","dataType":"varchar","fieldType":"many2one","relatedModelID":"lq_taxpayer_type"},
    {"field":"scjydz","name":"生产经营地址","dataType":"varchar","quickSearch":true},
    {"field":"zcdyzbm","name":"注册地邮政编码","dataType":"varchar","quickSearch":true},
    {"field":"zcdlxdh","name":"注册地联系电话","dataType":"varchar","quickSearch":true},
    {"field":"fddbrxm","name":"法人名称","dataType":"varchar","quickSearch":true},
    {"field":"djzclxdm","name":"登记注册类型","dataType":"varchar","quickSearch":true},
    {"field":"hydm","name":"行业代码","dataType":"varchar"},
    {"field":"qxjswjgdm","name":"区县级税务机关代码","dataType":"varchar"},
    {"field":"zgswskfjdm","name":"税务机关代码","dataType":"varchar"},
    {"field":"zgswskfjmc","name":"税务机关名称","dataType":"varchar"},
    {"field":"cwfzrxm","name":"财务负责人姓名","dataType":"varchar"},
    {"field":"khhmc","name":"账户名称","dataType":"varchar"},
    {"field":"yhzh","name":"账号","dataType":"varchar"},
    {"field":"bsrxm","name":"企业办税人员姓名","dataType":"varchar"},
    {"field":"xdpsdqybz","name":"数字化电子票试点企业标识","dataType":"varchar"},
    {"field":"ckqyfldm","name":"出口企业分类","dataType":"varchar","fieldType":"many2one","relatedModelID":"lq_exporter_type"},
    {"field":"zfjglxdm","name":"总分机构类型","dataType":"varchar","fieldType":"many2one","relatedModelID":"lq_head_branch_type"},
    {"field":"yhyywddm","name":"银行营业网点","dataType":"varchar"},
    {"field":"nsrztdm","name":"开票方纳税人状态","dataType":"varchar","fieldType":"many2one","relatedModelID":"lq_taxpayer_status"},
    {"field":"yxqq","name":"纳税人类型标签有效期起","dataType":"varchar"},
    {"field":"yxqz","name":"纳税人类型标签有效期止","dataType":"varchar"},
    {"field":"current","name":"是否当前记录","dataType":"varchar"},
    {"field":"create_time","name":"记录创建时间","dataType":"datetime"},
    {"field":"create_user","name":"记录创建人","dataType":"varchar"},
    {"field":"update_time","name":"记录更新时间","dataType":"datetime"},
    {"field":"update_user","name":"记录更新人","dataType":"varchar"},
    {"field":"version","name":"数据版本号","dataType":"int"},
    {"field":"lq_taxpayer_industry","name":"纳税人行业类型明细","fieldType":"one2many","relatedModelID":"lq_taxpayer_industry","relatedField":"lq_taxpayer_id"},
    {"field":"lq_taxpayer_consumer_type","name":"消费税纳税人类型明细","fieldType":"one2many","relatedModelID":"lq_taxpayer_consumer_type","relatedField":"lq_taxpayer_id"}
  ]
}